[
	{
		"question": "If you have 10 mangos and another person gives you 12 more, how‌ ‌many‌ ‌mangos‌ ‌will‌ ‌you‌ ‌have‌ ‌in‌ ‌total?‌",
		"options": [
			"1 mango",
			"2 mangos",
			"10 mangos",
			"22 mangos"
		],
		"answerIndex": [3]
	},
	{
		"question": "If‌ ‌a‌ ‌train‌ ‌is‌ ‌supposed‌ ‌to‌ ‌reach‌ ‌the‌ ‌station‌ ‌at‌ ‌4:10‌ ‌am‌. but‌ ‌it‌ ‌is ‌35‌ ‌minutes‌ late,‌ ‌at‌ ‌what‌ ‌time‌ ‌will ‌the‌ ‌train‌ ‌reach‌ ‌the‌ ‌station?‌ ‌",
		"options": [
			"4:45 am",
			"3:00 am",
			"4:45 pm",
			"6:00 pm"
		],
		"answerIndex": [0]
	},
	{
		"question": "Which of these animals can fly?‌",
		"options": [
			"Cats",
			"Bats",
			"Birds",
			"Worms"
		],
		"answerIndex": [1, 2]
	},
	{
		"question": "Which of the following is a list of colors?",
		"options": [
			"Dog, cat, fish",
			"Earth, Mars, Venus, Saturn, Mercury, Jupiter, Neptune, Uranus",
			"Guitar, drums, piano, harmonica, tambourine, trumpet",
			"Red, orange, yellow, green, blue, indigo, violet"
		],
		"answerIndex": [3]
	},
	{
		"question": "If you are reading a book and are on page 374, what will the number of the next page be?",
		"options": [
			"375",
			"373",
			"474",
			"400"
		],
		"answerIndex": [0]
	}
]